{"J2dYA2WzZIUav1modgdB/A==":"mbr-1620x1080.jpg","ckB/jDGnfH9mbWsDCvvdcA==":"mbr-865x1080.jpg","dkvg5b9o+XkpKV+yPScj6A==":"mbr-1-1620x1080.jpg","jSYmaZrr9+deK+RsoCELNw==":"batch_kakaotalk_2018-01-16-09-28-52_photo-57-1280x960.jpg","yahbC9gGjwpt+U9wNjPTSg==":"mbr-2-1620x1080.jpg","V7vUpUVrj2tfJSISVhg20A==":"mbr-1-865x1080.jpg","EkXcOFxTDGBqUficdc51Zw==":"mbr-720x1080.jpg","x6TAOh108vkXL60daOL6LQ==":"mbr-1-720x1080.jpg","cLcgj2KBGbtE2hhLK+38Fw==":"mbr-2-720x1080.jpg","rYEoJBap+ob0mTrtYqcbzQ==":"mbr-986x1080.jpg","h7gNB+NEuoCIywp2EkLeug==":"batch_kakaotalk_2018-01-16-09-28-49_photo-18-1280x960.jpg","+m18W05he8rN/12EANxbXw==":"mbr-3-720x1080.jpg","q2K3jS9Cl0yD/uay4ZWg9w==":"mbr-4-720x1080.jpg","IIcS5hrLrmw6SRFg+nL+Zw==":"mbr-1358x1080.jpg","SkOIArcAcJzKPoxio9v9UQ==":"slide3-1600x900.jpg","qxQVZsfnO0JmXMIqvPNNIA==":"mbr-754x1080.jpg","FzFNJOr4ug5kkVLll7l4gw==":"1-2000x1330.jpg","izEXmZ2//h5RQOZT7Du4wg==":"1-1-2000x1330.jpg","dzHC1DJn4yI9RIvuWPRrJw==":"2-2000x1331.jpg","ZkIpk6IVU0RsBum/yPK4sw==":"1-2-2000x1330.jpg","QjC7NO25PWaaqPRJX3CK0A==":"3-5472x3648.jpg","5H1eDakOwkAVDWAwXyGHfQ==":"3-1-5472x3648.jpg","UGZsMAxG6npeghpJXzpu6Q==":"3-2-5472x3648.jpg","eZ2xfzcIawKGVFmD7+CjLQ==":"3-3-5472x3648.jpg","+N7s/XagyCqT/S1RpJes/w==":"4-2128x1416.jpg","hkOERQ7aubcvkT4td4d7Vw==":"5-2126x1417.jpg","Svv90pZWNE9TbXKo1p1RbA==":"4-1-2128x1416.jpg","2iBR92OhYdMEVGBimQ0gKA==":"6-12490x6250.jpg","XLEvCHVotCNRxKkcJWugRg==":"7-2000x1330.jpg","n8dpsvlwIZMPq6dfndqxqw==":"7-1-2000x1330.jpg","OUBiX+3PWOTKJ4Yrg8uKug==":"8-2000x1330.jpg","58G+CogOGBKPHHoYQZ2G4g==":"8-1355x900.jpg","FyrjlGDr6f99T+lEuYuX9Q==":"9-2000x1330.jpg","UJXIctic0mdgPI7hBFpq+g==":"9-1355x900.jpg","XTUezsxrOoOFe/q41mNgpQ==":"10-2000x1330.jpg","1NeD3lXCGaVxtIdnfaCSow==":"10-1355x900.jpg","P+J0DJG0WoVD/NITk8ClfA==":"11-2000x1330.jpg","gtq8RlNaEiIQhGjp9mE9Jw==":"11-1355x900.jpg","8XZLjyuNL+23/kIjw6rk8A==":"12-2000x1330.jpg","FW/++nufHSgAasICfnIhcA==":"12-1355x900.jpg","ZO77wy5ZLy20wg6DSVYHUg==":"14-4912x7360.jpg","ZXXaeeDMFD9H7fBKZ4r4PA==":"15-4912x7360.jpg","yqLgW89fjMdYAVAhhI06CQ==":"16-4775x7154.jpg","2Gw5yYb8EZk5x93jPVL/iA==":"17-4912x7360.jpg","fl2ym6smumR6hGJYeLUysQ==":"15-1-4912x7360.jpg","s2fJvCs52C8oE8ybB4pK2w==":"16-1-4775x7154.jpg","M36qkiN16i0+siI/4koFbQ==":"17-1-4912x7360.jpg","9+8uNGicth7ud5Vd+VE9nQ==":"18-7360x4912.jpg","RcOrR7wuu/jmWtEHzI/Ofg==":"19-5472x3648.jpg","F2Bb148eJ26XPhUkfppgyw==":"20-965x544.png","IlU+nPs6ScL6/kHxjgOdwg==":"21-640x427.png","GPEKyQpE9qolfTJPeANhtg==":"22-886x590.png","CKXaJaPbzEIGoNjjEhboRg==":"batch-8-1280x851.jpg","gORSJH4yhL0ZbyryszYiaA==":"batch-8-1355x900.jpg","KRCbJ/MhI5Jj3ZMEqG+fjg==":"batch-9-1280x851.jpg","v6w3mX0ClADjYD58YS/A9A==":"batch-9-1355x900.jpg","56xDKvY6Pv4rHmbGl4zvxw==":"batch-10-1280x851.jpg","I1DnhXlyRFqHNh9JxB37BQ==":"batch-10-1355x900.jpg","1BdddnJC1VZgQLnfiixSiA==":"batch-11-1280x851.jpg","9/XGrdYStiy9qUEPNzAJGA==":"batch-11-1355x900.jpg","LLokDTpLhf9vIkHPAx6z9w==":"batch-12-1280x851.jpg","roUgKK37bsUyZe2+DuDFyg==":"batch-12-1355x900.jpg","BpG9hmDqmhBr/0YXsp3gBQ==":"batch-23-1280x853.jpg","PLMXI5KM9ysySUT4Je2+Og==":"batch-24-1280x1920.jpg","nPVqG0QpsloW5oj/4YxkTA==":"batch-25-1280x853.jpg","1BebAk+QRGoDg2FjncVPGw==":"batch-26-1280x1920.jpg","ZGtFKTXsGONjvi6kJY/VSw==":"batch-24-1280x853.jpg","YMpKhzC/eJw/FCHVZBEJCw==":"batch-26-1280x853.jpg","cQQNiJLr2E3bGuwDXxCdlw==":"batch-22-1280x852.png","Wv8z3hpSgmwD0oFbPOa9KQ==":"batch-14-1280x1917.jpg","OeqBPSh2s5rvtGommdXj3A==":"batch-15-1280x1917.jpg","w+ulpjPcF+n7NUr3nCDn5g==":"batch-18-1280x854.jpg","PX8QSRv4NN/QQkVNYOO0oA==":"batch-16-1280x1917.jpg","aGI/K6hxOJz1ddYV0Y9+WQ==":"batch-2-1280x852.jpg","bDVepknl1ZeeJd/OmJ/m1g==":"batch-3-1280x853.jpg","AOwNQy2YxAdV9VHxnqa1Kg==":"batch-4-1280x853.jpg","1OY3naPRAgc+NDSc6xnZCg==":"batch-4-1280x851.jpg","nix7MFb1e0fHS6fN4LLTKg==":"batch-6-1280x853.jpg","tOcO3io8lIywXTj5BB4oBw==":"batch-6-1280x640.jpg","wg5FtfSY2Cy19GV/au1wwg==":"batch-7-1280x851.jpg","EODzJ4k5ZXyC/xVJjt2Ikw==":"batch-17-1280x1917.jpg","6/8HpOnOho7i/0RRXHX3cQ==":"batch-18-1280x1917.jpg","WQQ2PnyLR/sIpAC3uXr6lA==":"batch-19-1280x1917.jpg","/2bggW0L6AtEDljEb2zLhA==":"batch-20-1280x1917.jpg","W1s7W1mjOLHQcD5bZNY4BA==":"batch-19-1280x854.jpg","Zx+KnAwjEtYFJFSZjzwjiA==":"batch-19-1280x853.jpg","PTwYGQBXnverrljSyVrCBg==":"batch-20-1280x721.png","iAaC24Fbc9vfF40cswD7BQ==":"batch-21-1280x854.png","Acii3UV3/d0lYghXJsdRyA==":"batch-23-1280x852.png","61vd5hVPDn84K6bxTsLnUw==":"batch-27-1280x853.jpg","Zmtkqo2EM4oqqtnAsPiDqQ==":"batch-28-1280x853.jpg","nTuwlgvWNIX3ez8Eza2WeA==":"batch-27-1280x1920.jpg","ae9uzAgnf9YHDyWKSbQYkA==":"1-3-2000x1330.jpg","qRbkGz2FvSFgnWfp9biNnQ==":"batch-8-1280x851.jpg","ovKp4bir5H8iJMns5j0bNQ==":"batch-8-1600x1063.jpg","Sr0h1Q6uAolLuU55/wnlvQ==":"batch-8-902x600.jpg","hK71evv9Jd0kbk3tqVNsXA==":"batch-12-1280x851.jpg","u56zvh7pH9ZyGWPJn31Y1g==":"batch-12-1600x1063.jpg","LJSJMFd97mDuvgL685wiFA==":"batch-11-1280x851.jpg","w0/dKsPmQpbBo4K2GgiNSQ==":"batch-11-1600x1063.jpg","PqKa9C76sqd3QZhnjiAEHQ==":"batch-9-1280x851.jpg","wg2j991lUYDl+dxAz2Z3Aw==":"batch-9-1600x1063.jpg","gdLtZYdbp4fV7sJQjQymeA==":"batch-10-1280x851.jpg","OLc7S6XQGehrJ4EplFCh9A==":"batch-10-1600x1063.jpg","yEZ+QBUARsVd/k1ElBs1Fg==":"batch-26-1280x1920.jpg","XJZLmxnHDwgr9blVWWG3Vg==":"batch-21-1280x1917.jpg","ywoasNS7ZRu8s/Chxs+TJA==":"batch-13-1280x851.jpg","yRRUsqqpDn8Rs2b92lp90g==":"batch-3-1280x853.jpg"}